LICENSE.txt
MANIFEST.in
README.md
requirements.txt
setup.py
rabbitmq_rpc/__init__.py
rabbitmq_rpc/base.py
rabbitmq_rpc/client.py
rabbitmq_rpc/consumer.py
rabbitmq_rpc/credentials.py
rabbitmq_rpc/exceptions.py
rabbitmq_rpc/main.py
rabbitmq_rpc/queue.py
rabbitmq_rpc/server.py
rabbitmq_rpc/threadtool.py
rabbitmq_rpc/utils.py
rabbitmq_rpc.egg-info/PKG-INFO
rabbitmq_rpc.egg-info/SOURCES.txt
rabbitmq_rpc.egg-info/dependency_links.txt
rabbitmq_rpc.egg-info/entry_points.txt
rabbitmq_rpc.egg-info/requires.txt
rabbitmq_rpc.egg-info/top_level.txt
rabbitmq_rpc/commands/__init__.py
rabbitmq_rpc/commands/base.py
rabbitmq_rpc/commands/worker.py