Metadata-Version: 2.1
Name: rabbitmq-rpc
Version: 0.1.10
Summary: A modified rabbit-rpc of https://github.com/MidTin/rabbit-rpc
Home-page: https://github.com/liupgd/rabbitmq_rpc
Author: leo
Author-email: liupgd@foxmail.com
License: MIT
Platform: any
Classifier: License :: OSI Approved :: MIT License
Classifier: Intended Audience :: Developers
Classifier: Operating System :: OS Independent
Classifier: Topic :: Software Development :: Libraries
Classifier: Programming Language :: Python :: 3
Classifier: Programming Language :: Python :: 3.4
Classifier: Programming Language :: Python :: 3.5
Classifier: Programming Language :: Python :: 3.6
Classifier: Programming Language :: Python :: 3.7
Classifier: Programming Language :: Python :: 3.8
Classifier: Programming Language :: Python :: Implementation :: CPython
